wkstools/__init__.py
wkstools/models.py
wkstools/wkstools.py
wkstools-0.1.2.dist-info/LICENSE
wkstools-0.1.2.dist-info/WHEEL
wkstools-0.1.2.dist-info/METADATA
wkstools-0.1.2.dist-info/RECORD
