Metadata-Version: 2.1
Name: wkstools
Version: 0.1.2
Summary: IBM Watson Natural Language Understanding + Watson Knowledge Studio tools 
Home-page: https://github.com/eightBEC
License: UNKNOWN
Author: Jan Forster
Author-email: eightbec@gmail.com
Requires-Python: >=3.6
Classifier: Intended Audience :: Information Technology
Classifier: Intended Audience :: System Administrators
Classifier: Operating System :: OS Independent
Classifier: Programming Language :: Python :: 3
Classifier: Programming Language :: Python
Classifier: Topic :: Software Development :: Libraries :: Python Modules
Classifier: Topic :: Software Development :: Libraries
Classifier: Topic :: Software Development
Classifier: Typing :: Typed
Classifier: Development Status :: 4 - Beta
Classifier: Intended Audience :: Developers
Classifier: License :: OSI Approved :: MIT License
Classifier: Programming Language :: Python :: 3 :: Only
Classifier: Programming Language :: Python :: 3.6
Classifier: Programming Language :: Python :: 3.7
Classifier: Programming Language :: Python :: 3.8
Requires-Dist: pydantic==1.6.1
Requires-Dist: pytest ==6.0.1 ; extra == "test"
Requires-Dist: pytest-cov ==2.10.0 ; extra == "test"
Requires-Dist: mypy ==0.782 ; extra == "test"
Requires-Dist: black ==19.10b0 ; extra == "test"
Requires-Dist: bandit ==1.6.2 ; extra == "test"
Requires-Dist: flake8 ==3.8.3 ; extra == "test"
Provides-Extra: test
